instagram_locations/__init__.py
instagram_locations/instagram_locations.py
instagram_locations/version.py
instagram_location_search-1.5.2.dist-info/LICENSE
instagram_location_search-1.5.2.dist-info/METADATA
instagram_location_search-1.5.2.dist-info/WHEEL
instagram_location_search-1.5.2.dist-info/entry_points.txt
instagram_location_search-1.5.2.dist-info/top_level.txt
instagram_location_search-1.5.2.dist-info/RECORD
