Metadata-Version: 2.1
Name: instagram-location-search
Version: 1.5.2
Summary: Finds Instagram location IDs near a specified latitude and longitude.
Home-page: https://www.bellingcat.com
Author: Bellingcat
Author-email: tech@bellingcat.com
License: MIT License
Classifier: Intended Audience :: Information Technology
Classifier: License :: OSI Approved :: MIT License
Classifier: Operating System :: OS Independent
Classifier: Natural Language :: English
Classifier: Programming Language :: Python :: 3
License-File: LICENSE
Requires-Dist: requests
Requires-Dist: numpy
Requires-Dist: pandas
Requires-Dist: selenium
Requires-Dist: webdriver-manager
